LICENSE
README.md
setup.py
zh_normalization/__init__.py
zh_normalization/char_convert.py
zh_normalization/chronology.py
zh_normalization/constants.py
zh_normalization/num.py
zh_normalization/phonecode.py
zh_normalization/quantifier.py
zh_normalization/text_normlization.py
zh_normalization.egg-info/PKG-INFO
zh_normalization.egg-info/SOURCES.txt
zh_normalization.egg-info/dependency_links.txt
zh_normalization.egg-info/requires.txt
zh_normalization.egg-info/top_level.txt