Metadata-Version: 2.1
Name: zh-normalization
Version: 0.0.1
Summary: Chinese Text Normalization(for speech recognition and text to speech)
Home-page: https://github.com/shibing624/zh-normalization
Author: XuMing
Author-email: xuming624@qq.com
License: Apache 2.0
Keywords: TTS,ASR,text to speech,speech
Platform: Windows
Platform: Linux
Platform: Solaris
Platform: Mac OS-X
Platform: Unix
Classifier: Intended Audience :: Developers
Classifier: Operating System :: OS Independent
Classifier: Natural Language :: Chinese (Simplified)
Classifier: Natural Language :: Chinese (Traditional)
Classifier: Programming Language :: Python
Classifier: Programming Language :: Python :: 3
Classifier: Topic :: Software Development :: Libraries :: Python Modules
Classifier: Topic :: Scientific/Engineering :: Artificial Intelligence
License-File: LICENSE
